zgpt/__init__.py
zgpt/api.py
zgpt/cli.py
zgpt/config.py
zgpt-1.0.1.dist-info/METADATA
zgpt-1.0.1.dist-info/WHEEL
zgpt-1.0.1.dist-info/entry_points.txt
zgpt-1.0.1.dist-info/top_level.txt
zgpt-1.0.1.dist-info/RECORD
