Metadata-Version: 2.4
Name: zgpt
Version: 1.0.1
Summary: A versatile CLI assistant powered by the Gemini API.
Home-page: https://github.com/sachinz25/zgpt
Author: sachinz25
Classifier: Programming Language :: Python :: 3
Classifier: License :: OSI Approved :: MIT License
Classifier: Operating System :: OS Independent
Requires-Python: >=3.7
Requires-Dist: requests>=2.25.0
Dynamic: author
Dynamic: classifier
Dynamic: description
Dynamic: description-content-type
Dynamic: home-page
Dynamic: requires-dist
Dynamic: requires-python
Dynamic: summary
